flask_mailjet/__init__.py
flask_mailjet/loader.py
flask_mailjet/mailjet.py
flask_mailjet/templates/mailjet/base.html
flask_mailjet-0.3.7.dist-info/licenses/LICENSE
flask_mailjet-0.3.7.dist-info/METADATA
flask_mailjet-0.3.7.dist-info/WHEEL
flask_mailjet-0.3.7.dist-info/top_level.txt
flask_mailjet-0.3.7.dist-info/RECORD
