Metadata-Version: 2.4
Name: flask_mailjet
Version: 0.3.7
Summary: A Flask extension for sending emails via Mailjet API.
Author-email: Tim Kadlec <tim@mwq.cz>
License-Expression: MIT
Classifier: Programming Language :: Python :: 3
Classifier: Operating System :: OS Independent
Classifier: Framework :: Flask
Classifier: Topic :: Communications :: Email
Requires-Python: >=3.8
License-File: LICENSE
Requires-Dist: Flask>=2.0
Requires-Dist: mailjet-rest>=1.3.4
Requires-Dist: pytest>=8.3.5
Dynamic: license-file
